{
  "library": [
    {
      "id": 1,
      "name": "Cây cam ngọt của tôi",
      "author": "Jose Mauro de Vansconcelos",
      "category": [
        {
          "id": 1,
          "name": "Tiểu thuyết"
        }
      ]
    },
    {
      "id": 2,
      "name": "Trốn lên mái nhà để khóc",
      "author": "Lam",
      "category": [
        {
          "id": 2,
          "name": "Truyện vừa"
        }
      ]
    },
    {
      "id": 3,
      "name": "Thất lạc cõi người",
      "author": "Dazai osamu",
      "category": [
        {
          "id": 3,
          "name": "Tiểu thuyết"
        }
      ]
    }
  ]
}
